{
  "quick-sort": {
    "id": "quick-sort",
    "metadata": {
      "title": "Quick Sort",
      "subtitle": "Efficient, in-place divide-and-conquer sorting algorithm",
      "category": "Sorting",
      "tags": ["Divide & Conquer", "In-place", "Sorting", "Recursive"],
      "stability": "unstable"
    },
    "complexity": {
      "time": {
        "best": "\\Theta(n \\log n)",
        "average": "\\Theta(n \\log n)",
        "worst": "\\Theta(n^2)",
        "worst_weight": 5
      },
      "space": {
        "average": "\\Theta(\\log n)",
        "notes": "Sorts in-place, but requires expected $\\Theta(\\log n)$ space for the recursion call stack. In the worst-case (unbalanced partitions), the space complexity can degrade to $O(n)$ if tail-call optimization is not implemented."
      },
      "recurrence_relation": "$T(n) = 2T(n/2) + \\Theta(n)$"
    },
    "documentation": {
      "description": "Quicksort is an efficient, in-place sorting algorithm that uses the divide-and-conquer paradigm. It partitions an array into two subarrays around a pivot element and recursively sorts them.",
      "how_it_works": [
        "Divide: Select a pivot element from the array and partition the elements such that all elements less than or equal to the pivot are placed to its left, and all strictly greater elements are placed to its right.",
        "Conquer: Recursively call the quicksort algorithm on the two subarrays (left of the pivot and right of the pivot).",
        "Combine: Because the subarrays are sorted in place, no explicit combination step is needed to merge them. The entire array is sorted."
      ],
      "applications": [
        "It is widely used as a general-purpose sorting algorithm in standard libraries (e.g., C++ std::sort utilizes Introsort, which is based on Quicksort) due to its excellent average-case performance and small constant factors.",
        "It works exceptionally well in virtual-memory environments because of its good cache locality and sequential memory access patterns."
      ],
      "pitfalls": [
        "The worst-case time complexity of $\\Theta(n^2)$ occurs when the array is already sorted or reverse sorted and a naive pivot strategy (like choosing the last element) is used.",
        "To mitigate worst-case scenarios, a randomized pivot selection (Randomized Quicksort) or the Median-of-3 method should be implemented."
      ],
      "comparisons": [
        {
          "alternative_to": "merge-sort",
          "reason": "Merge sort provides a guaranteed worst-case time complexity of $\\Theta(n \\log n)$ and is stable, unlike quicksort. However, quicksort operates in-place requiring only $\\Theta(\\log n)$ space, and generally outperforms merge sort in practice due to smaller constant factors and superior cache locality."
        }
      ]
    },
    "implementations": [
      {
        "language": "pseudocode",
        "snippet": "QUICKSORT(A, p, r)\n  if p < r\n    q = PARTITION(A, p, r)\n    QUICKSORT(A, p, q - 1)\n    QUICKSORT(A, q + 1, r)\n\nPARTITION(A, p, r)\n  x = A[r]\n  i = p - 1\n  for j = p to r - 1\n    if A[j] <= x\n      i = i + 1\n      exchange A[i] with A[j]\n  exchange A[i + 1] with A[r]\n  return i + 1",
        "explanation": "This pseudocode implements the Lomuto partition scheme using 0-indexed bounds. p is the starting index and r is the ending index (inclusive)."
      },
      {
        "language": "cpp",
        "snippet": "#include <vector>\n#include <algorithm>\n\nusing namespace std;\n\nint partition(vector<int>& A, int p, int r) {\n    int pivot = A[r];\n    int i = p - 1;\n    for (int j = p; j < r; j++) {\n        if (A[j] <= pivot) {\n            i++;\n            swap(A[i], A[j]);\n        }\n    }\n    swap(A[i + 1], A[r]);\n    return i + 1;\n}\n\nvoid quickSort(vector<int>& A, int p, int r) {\n    if (p < r) {\n        int q = partition(A, p, r);\n        quickSort(A, p, q - 1);\n        quickSort(A, q + 1, r);\n    }\n}",
        "explanation": "A real-world C++ implementation operating on std::vector<int>. It mimics the 0-indexed pseudocode perfectly."
      }
    ],
    "visualizer_config": {
      "type": "bars",
      "default_data_size": 50,
      "default_data_pattern": "random",
      "complexity_level": "intermediate"
    },
    "citations": [
      {
        "source_name": "Introduction to Algorithms, Third Edition (CLRS)",
        "authors": "Thomas H. Cormen, Charles E. Leiserson, Ronald L. Rivest, Clifford Stein",
        "chapter_or_page": "Chapter 7: Quicksort, Sections 7.1 - 7.4"
      }
    ]
  },
  "bubble-sort": {
    "id": "bubble-sort",
    "metadata": {
      "title": "Bubble Sort",
      "subtitle": "Simple exchange-based sorting",
      "category": "Sorting",
      "tags": ["Simple", "Stable", "In-place"],
      "stability": "stable"
    },
    "complexity": {
      "time": {
        "best": "\\Theta(n)",
        "average": "\\Theta(n^2)",
        "worst": "\\Theta(n^2)",
        "worst_weight": 5
      },
      "space": {
        "average": "\\Theta(1)",
        "notes": "Requires only a single additional memory space for the swap variable."
      }
    },
    "documentation": {
      "description": "A simple sorting algorithm that repeatedly steps through the list, compares adjacent elements and swaps them if they are in the wrong order.",
      "how_it_works": [
        "Iterate through the array from the first element.",
        "Compare each pair of adjacent elements.",
        "Swap them if they are in the wrong order (ascending/descending).",
        "Repeat until no more swaps are needed."
      ],
      "applications": [
        "Educational purposes due to its extreme simplicity.",
        "Detecting a nearly sorted array in $O(n)$ time."
      ]
    },
    "implementations": [
      {
        "language": "javascript",
        "snippet": "function bubbleSort(arr) {\n  let n = arr.length;\n  for (let i = 0; i < n; i++) {\n    for (let j = 0; j < n - i - 1; j++) {\n      if (arr[j] > arr[j + 1]) {\n        [arr[j], arr[j+1]] = [arr[j+1], arr[j]];\n      }\n    }\n  }\n  return arr;\n}",
        "explanation": "Standard nested loop implementation. The inner loop gets shorter as larger elements 'bubble' to the end."
      }
    ],
    "visualizer_config": {
      "type": "bars",
      "default_data_size": 12,
      "default_data_pattern": "random",
      "complexity_level": "beginner"
    }
  },
  "merge-sort": {
    "id": "merge-sort",
    "metadata": {
      "title": "Merge Sort",
      "subtitle": "Stable divide and conquer sorting",
      "category": "Sorting",
      "tags": ["Divide & Conquer", "Stable", "Recursive"],
      "stability": "stable"
    },
    "complexity": {
      "time": {
        "best": "\\Theta(n \\log n)",
        "average": "\\Theta(n \\log n)",
        "worst": "\\Theta(n \\log n)",
        "worst_weight": 4
      },
      "space": {
        "average": "\\Theta(n)",
        "notes": "Requires auxiliary space proportional to the size of the array for merging subarrays."
      },
      "recurrence_relation": "$T(n) = 2T(n/2) + \\Theta(n)$"
    },
    "documentation": {
      "description": "A divide-and-conquer algorithm that was invented by John von Neumann in 1945. It divides the input array into two halves, calls itself for the two halves, and then merges the two sorted halves.",
      "how_it_works": [
        "Divide: Split the array into two halves.",
        "Conquer: Recursively sort the two halves.",
        "Combine: Merge the two sorted halves back together into a single sorted array."
      ],
      "applications": [
        "Sorting linked lists in $O(n \\log n)$ time with $O(1)$ extra space.",
        "External sorting (sorting large data that doesn't fit in RAM)."
      ]
    },
    "implementations": [
      {
        "language": "javascript",
        "snippet": "function mergeSort(arr) {\n  if (arr.length <= 1) return arr;\n  const mid = Math.floor(arr.length / 2);\n  const left = mergeSort(arr.slice(0, mid));\n  const right = mergeSort(arr.slice(mid));\n  return merge(left, right);\n}",
        "explanation": "Recursive split implementation using array slicing."
      }
    ],
    "visualizer_config": {
      "type": "bars",
      "default_data_size": 20,
      "default_data_pattern": "random",
      "complexity_level": "intermediate"
    }
  }
}